autostack/__init__.py
autostack/main.py
autostack/web_scraper/__init__.py
autostack/web_scraper/stack_overflow_scraper.py
autostack-0.0.11.data/scripts/autostack-terminal
autostack-0.0.11.dist-info/LICENSE
autostack-0.0.11.dist-info/METADATA
autostack-0.0.11.dist-info/WHEEL
autostack-0.0.11.dist-info/entry_points.txt
autostack-0.0.11.dist-info/top_level.txt
autostack-0.0.11.dist-info/RECORD
