Metadata-Version: 2.1
Name: autostack
Version: 0.0.11
Summary: Automatically detect python errors and search Stack Overflow.
Home-page: https://github.com/elijahsawyers/AutoStack
Author: Elijah Sawyers, Benjamin Sanders, Caleb Werth
Author-email: elijahsawyers@gmail.com, ben.sanders97@gmail.com, cwerth@crimson.ua.edu
License: UNKNOWN
Platform: UNKNOWN
Classifier: Development Status :: 3 - Alpha
Classifier: Intended Audience :: Developers
Classifier: Topic :: Software Development :: Debuggers
Classifier: Programming Language :: Python :: 3
Classifier: License :: OSI Approved :: MIT License
Classifier: Operating System :: Unix
Requires-Dist: Pygments (>=2.3.1)
Requires-Dist: requests (>=2.21.0)
Requires-Dist: termcolor (>=1.1.0)
Requires-Dist: lxml (>=4.3.2)
Requires-Dist: beautifulsoup4 (>=4.7.1)
Requires-Dist: future (>=0.17.1)
